{
 "execution": {
  "type": "VplatExecutioner"
 },
 "graphs": [
  {
   "model_group": "ZFAddModels",
   "model_name": "ZF_Valution",
   "order_logics": [
    {
     "max_depth_": 3,
     "max_order_size_": 3,
     "max_orders_per_side_": 4,
     "name": "10BasicMaker-Valuation_AeXw",
     "order_scorer": {
      "add_edge_": 0.0,
      "cancel_edge_": -0.00078125,
      "max_qspot_": {
       "filled_qspot_": {
        "split_md_": {
         "config_": {
          "exchDt_begin": -9223372036854775808,
          "exchDt_end": 9223372036854775807,
          "humanSize_": false,
          "initialQty_begin": 0,
          "initialQty_end": 2147483647,
          "qtyCap_": 10,
          "receiveDt_begin": -9223372036854775808,
          "receiveDt_end": 9223372036854775807,
          "refreshMult_": 0.0,
          "type": "SplitMarketData::Config",
          "useSplitBookInTrades": true
         },
         "symbol_": "CME:ZF%0Q",
         "type": "SplitMarketData"
        },
        "type": "FilledInitQSpot"
       },
       "markup_horizons_": [
        30000000000,
        5000000000
       ],
       "max_init_value_": 1000.0,
       "min_init_value_": -1000.0,
       "step_size_": 1.0,
       "type": "MaxQSpotByEdge",
       "valuation_": {
        "config_": {
         "name": "Valuation_AeXw",
         "symbol": "CME:ZF%0Q",
         "valuation": [
          {
           "signal": {
            "half_impact_size_": 500.0,
            "length_in_ticks_": 2000.0,
            "market_data_": {
             "symbol_": "CME:ZT%0Q",
             "type": "RawMarketData_Event"
            },
            "name": "SigmoidSVZT_500c2000t_4397",
            "type": "SigmoidSV"
           },
           "weight": 0.0001007627875517353
          },
          {
           "signal": {
            "fast_half_impact_size_": 100.0,
            "fast_length_in_ticks_": 10,
            "market_data_": {
             "config_": {
              "exchDt_begin": 10000,
              "exchDt_end": 9223372036854775807,
              "humanSize_": false,
              "initialQty_begin": 0,
              "initialQty_end": 2147483647,
              "qtyCap_": 2147483647,
              "receiveDt_begin": -9223372036854775808,
              "receiveDt_end": 9223372036854775807,
              "type": "SplitMarketData::Config",
              "useSplitBookInTrades": true
             },
             "symbol_": "CME:ZF%0Q",
             "type": "SplitMarketData"
            },
            "name": "PersistentSVZF_100c10t_1000c100tSlow10us_1217",
            "slow_half_impact_size_": 1000.0,
            "slow_length_in_ticks_": 100,
            "type": "PersistentSV"
           },
           "weight": 0.00017693910733932068
          },
          {
           "signal": {
            "half_impact_size_": 500.0,
            "length_in_ticks_": 2000.0,
            "market_data_": {
             "symbol_": "CME:ZN%0Q",
             "type": "RawMarketData_Event"
            },
            "name": "SigmoidSVZN_500c2000t_5560",
            "type": "SigmoidSV"
           },
           "weight": 0.000883127118472619
          },
          {
           "signal": {
            "fast_half_impact_size_": 100.0,
            "fast_length_in_ticks_": 10,
            "market_data_": {
             "config_": {
              "exchDt_begin": -9223372036854775808,
              "exchDt_end": 9223372036854775807,
              "humanSize_": false,
              "initialQty_begin": 0,
              "initialQty_end": 10,
              "qtyCap_": 2147483647,
              "receiveDt_begin": -9223372036854775808,
              "receiveDt_end": 9223372036854775807,
              "type": "SplitMarketData::Config",
              "useSplitBookInTrades": true
             },
             "symbol_": "CME:ZF%0Q",
             "type": "SplitMarketData"
            },
            "name": "PersistentSVZF_100c10t_1000c100tSmall10_5420",
            "slow_half_impact_size_": 1000.0,
            "slow_length_in_ticks_": 100,
            "type": "PersistentSV"
           },
           "weight": 0.001294890467701194
          },
          {
           "signal": {
            "fill_depth_": 2,
            "market_data_": {
             "config_": {
              "exchDt_begin": -9223372036854775808,
              "exchDt_end": 9223372036854775807,
              "humanSize_": false,
              "initialQty_begin": 0,
              "initialQty_end": 50,
              "qtyCap_": 2147483647,
              "receiveDt_begin": -9223372036854775808,
              "receiveDt_end": 9223372036854775807,
              "type": "SplitMarketData::Config",
              "useSplitBookInTrades": false
             },
             "symbol_": "CME:ZF%0Q",
             "type": "SplitMarketData"
            },
            "name": "FillAveSizeZFSmall50MD2_3908",
            "size_depth_": 2,
            "size_ema_length_": 100000.0,
            "size_mult_": 0.5,
            "type": "FillAve",
            "use_counts_": false
           },
           "weight": 0.2755638769697063
          },
          {
           "signal": {
            "fill_depth_": 2,
            "market_data_": {
             "config_": {
              "exchDt_begin": 10000,
              "exchDt_end": 9223372036854775807,
              "humanSize_": false,
              "initialQty_begin": 0,
              "initialQty_end": 50,
              "qtyCap_": 2147483647,
              "receiveDt_begin": -9223372036854775808,
              "receiveDt_end": 9223372036854775807,
              "type": "SplitMarketData::Config",
              "useSplitBookInTrades": false
             },
             "symbol_": "CME:ZF%0Q",
             "type": "SplitMarketData"
            },
            "name": "FillAveSizeZFSlow10usSmall50MD2_6624",
            "size_depth_": 2,
            "size_ema_length_": 100000.0,
            "size_mult_": 0.5,
            "type": "FillAve",
            "use_counts_": false
           },
           "weight": 0.12030426337298285
          },
          {
           "signal": {
            "fill_depth_": 2,
            "market_data_": {
             "config_": {
              "exchDt_begin": 1000000,
              "exchDt_end": 9223372036854775807,
              "humanSize_": false,
              "initialQty_begin": 10,
              "initialQty_end": 2147483647,
              "qtyCap_": 2147483647,
              "receiveDt_begin": -9223372036854775808,
              "receiveDt_end": 9223372036854775807,
              "type": "SplitMarketData::Config",
              "useSplitBookInTrades": false
             },
             "symbol_": "CME:ZF%0Q",
             "type": "SplitMarketData"
            },
            "name": "FillAveSizeZFSlow1msBig10MD2_7086",
            "size_depth_": 2,
            "size_ema_length_": 100000.0,
            "size_mult_": 0.5,
            "type": "FillAve",
            "use_counts_": false
           },
           "weight": 0.12382430439836066
          },
          {
           "signal": {
            "half_impact_size_": 1.0,
            "length_in_ticks_": 20.0,
            "market_data_": {
             "symbol_": "CME:ZN%0Q",
             "type": "RawMarketData_Event"
            },
            "name": "SigmoidSVZN_1c20t_2901",
            "type": "SigmoidSV"
           },
           "weight": 0.0004356762231873615
          },
          {
           "signal": {
            "half_impact_size1_": 30.0,
            "half_impact_size2_": 20.0,
            "length_in_ticks_": 50,
            "md1_": {
             "symbol_": "CME:ZF%0Q",
             "type": "RawMarketData_Event"
            },
            "md2_": {
             "symbol_": "CME:ZN%0Q",
             "type": "RawMarketData_Event"
            },
            "name": "ProdSVZFZN_30c50t_20c50t_5075",
            "type": "ProdSV"
           },
           "weight": 8.400126816331024e-05
          },
          {
           "signal": {
            "base_theo_": {
             "fill_depth_": 4,
             "market_data_": {
              "config_": {
               "exchDt_begin": -9223372036854775808,
               "exchDt_end": 9223372036854775807,
               "humanSize_": false,
               "initialQty_begin": 0,
               "initialQty_end": 2147483647,
               "qtyCap_": 10,
               "receiveDt_begin": -9223372036854775808,
               "receiveDt_end": 9223372036854775807,
               "type": "SplitMarketData::Config",
               "useSplitBookInTrades": false
              },
              "symbol_": "CME:ZF%0Q",
              "type": "SplitMarketData"
             },
             "size_depth_": 3,
             "size_ema_length_": 100000.0,
             "size_mult_": 1.0,
             "type": "FillAve",
             "use_counts_": false
            },
            "intensity_mult_": 10000.0,
            "long_decay_": 600000000000,
            "name": "TICTZFFillAveSizeZN10m10ms10000t55vm_1348",
            "ref_theo_": {
             "fill_depth_": 4,
             "market_data_": {
              "config_": {
               "exchDt_begin": -9223372036854775808,
               "exchDt_end": 9223372036854775807,
               "humanSize_": false,
               "initialQty_begin": 0,
               "initialQty_end": 2147483647,
               "qtyCap_": 10,
               "receiveDt_begin": -9223372036854775808,
               "receiveDt_end": 9223372036854775807,
               "type": "SplitMarketData::Config",
               "useSplitBookInTrades": false
              },
              "symbol_": "CME:ZN%0Q",
              "type": "SplitMarketData"
             },
             "size_depth_": 3,
             "size_ema_length_": 100000.0,
             "size_mult_": 1.0,
             "type": "FillAve",
             "use_counts_": false
            },
            "short_decay_": 10000000,
            "type": "TradeIntensityCompTheo",
            "vol_mult_": 0.5551515151515152
           },
           "weight": 0.06232185720271092
          },
          {
           "signal": {
            "base_theo_": {
             "fill_depth_": 4,
             "market_data_": {
              "config_": {
               "exchDt_begin": -9223372036854775808,
               "exchDt_end": 9223372036854775807,
               "humanSize_": false,
               "initialQty_begin": 0,
               "initialQty_end": 2147483647,
               "qtyCap_": 10,
               "receiveDt_begin": -9223372036854775808,
               "receiveDt_end": 9223372036854775807,
               "type": "SplitMarketData::Config",
               "useSplitBookInTrades": false
              },
              "symbol_": "CME:ZF%0Q",
              "type": "SplitMarketData"
             },
             "size_depth_": 3,
             "size_ema_length_": 100000.0,
             "size_mult_": 1.0,
             "type": "FillAve",
             "use_counts_": false
            },
            "ema_length_": 600000000000,
            "name": "TimeCompTheoZFFillAveSizeZT10m244vm_1653",
            "ref_theo_": {
             "fill_depth_": 4,
             "market_data_": {
              "config_": {
               "exchDt_begin": -9223372036854775808,
               "exchDt_end": 9223372036854775807,
               "humanSize_": false,
               "initialQty_begin": 0,
               "initialQty_end": 2147483647,
               "qtyCap_": 10,
               "receiveDt_begin": -9223372036854775808,
               "receiveDt_end": 9223372036854775807,
               "type": "SplitMarketData::Config",
               "useSplitBookInTrades": false
              },
              "symbol_": "CME:ZT%0Q",
              "type": "SplitMarketData"
             },
             "size_depth_": 3,
             "size_ema_length_": 100000.0,
             "size_mult_": 1.0,
             "type": "FillAve",
             "use_counts_": false
            },
            "type": "TimeCompTheo",
            "vol_mult_": 2.4426666666666668
           },
           "weight": 0.014834781948862237
          },
          {
           "signal": {
            "base_theo_": {
             "fill_depth_": 4,
             "market_data_": {
              "config_": {
               "exchDt_begin": -9223372036854775808,
               "exchDt_end": 9223372036854775807,
               "humanSize_": false,
               "initialQty_begin": 0,
               "initialQty_end": 2147483647,
               "qtyCap_": 10,
               "receiveDt_begin": -9223372036854775808,
               "receiveDt_end": 9223372036854775807,
               "type": "SplitMarketData::Config",
               "useSplitBookInTrades": false
              },
              "symbol_": "CME:ZF%0Q",
              "type": "SplitMarketData"
             },
             "size_depth_": 3,
             "size_ema_length_": 100000.0,
             "size_mult_": 1.0,
             "type": "FillAve",
             "use_counts_": false
            },
            "intensity_mult_": 10000.0,
            "long_decay_": 600000000000,
            "name": "TICTZFFillAveSizeZT10m10s10000t244vm_1336",
            "ref_theo_": {
             "fill_depth_": 4,
             "market_data_": {
              "config_": {
               "exchDt_begin": -9223372036854775808,
               "exchDt_end": 9223372036854775807,
               "humanSize_": false,
               "initialQty_begin": 0,
               "initialQty_end": 2147483647,
               "qtyCap_": 10,
               "receiveDt_begin": -9223372036854775808,
               "receiveDt_end": 9223372036854775807,
               "type": "SplitMarketData::Config",
               "useSplitBookInTrades": false
              },
              "symbol_": "CME:ZT%0Q",
              "type": "SplitMarketData"
             },
             "size_depth_": 3,
             "size_ema_length_": 100000.0,
             "size_mult_": 1.0,
             "type": "FillAve",
             "use_counts_": false
            },
            "short_decay_": 10000000000,
            "type": "TradeIntensityCompTheo",
            "vol_mult_": 2.4426666666666668
           },
           "weight": 0.09821639797430351
          },
          {
           "signal": {
            "market_data_": {
             "symbol_": "CME:ZF%0Q",
             "type": "RawMarketData_Event"
            },
            "name": "TimeVWAPCompTheoZFMidptZN10ms100vm_1428",
            "nano_vwap_length_": 10000000,
            "ref_theo_": {
             "market_data_": {
              "symbol_": "CME:ZN%0Q",
              "type": "RawMarketData_Event"
             },
             "type": "Midpt"
            },
            "type": "TimeVWAPCompTheo",
            "vol_mult_": 1.0
           },
           "weight": 0.011877958473329094
          },
          {
           "signal": {
            "fill_depth_": 2,
            "market_data_": {
             "symbol_": "CME:ZF%0Q",
             "type": "IcebergTotalRefresh"
            },
            "name": "FillAveSizeZFIcebergRefreshMD3_8128",
            "size_depth_": 3,
            "size_ema_length_": 100000.0,
            "size_mult_": 1.0,
            "type": "FillAve",
            "use_counts_": false
           },
           "weight": 0.041298804587319604
          },
          {
           "signal": {
            "market_data_": {
             "config_": {
              "exchDt_begin": 10000,
              "exchDt_end": 9223372036854775807,
              "humanSize_": false,
              "initialQty_begin": 0,
              "initialQty_end": 2147483647,
              "qtyCap_": 2147483647,
              "receiveDt_begin": -9223372036854775808,
              "receiveDt_end": 9223372036854775807,
              "type": "SplitMarketData::Config",
              "useSplitBookInTrades": true
             },
             "symbol_": "CME:ZF%0Q",
             "type": "SplitMarketData"
            },
            "min_size_": 1,
            "name": "DurationSVZF_1c1msSlow10us_3868",
            "nanos_": 1000000,
            "type": "DurationSV"
           },
           "weight": 9.786430465597851e-05
          },
          {
           "signal": {
            "fill_depth_": 2,
            "market_data_": {
             "config_": {
              "exchDt_begin": -9223372036854775808,
              "exchDt_end": 9223372036854775807,
              "humanSize_": true,
              "initialQty_begin": 0,
              "initialQty_end": 2147483647,
              "qtyCap_": 2147483647,
              "receiveDt_begin": -9223372036854775808,
              "receiveDt_end": 9223372036854775807,
              "type": "SplitMarketData::Config",
              "useSplitBookInTrades": true
             },
             "symbol_": "CME:ZF%0Q",
             "type": "SplitMarketData"
            },
            "name": "FillAveSizeZFHumanSizeMD2_5400",
            "size_depth_": 2,
            "size_ema_length_": 100000.0,
            "size_mult_": 0.5,
            "type": "FillAve",
            "use_counts_": false
           },
           "weight": 0.10076216309126965
          },
          {
           "signal": {
            "market_data_": {
             "config_": {
              "exchDt_begin": -9223372036854775808,
              "exchDt_end": 9223372036854775807,
              "humanSize_": true,
              "initialQty_begin": 0,
              "initialQty_end": 2147483647,
              "qtyCap_": 2147483647,
              "receiveDt_begin": -9223372036854775808,
              "receiveDt_end": 9223372036854775807,
              "type": "SplitMarketData::Config",
              "useSplitBookInTrades": true
             },
             "symbol_": "CME:ZF%0Q",
             "type": "SplitMarketData"
            },
            "min_size_": 1,
            "name": "DurationSVZF_1c1msHuman_5936",
            "nanos_": 1000000,
            "type": "DurationSV"
           },
           "weight": 8.372296697687381e-05
          },
          {
           "signal": {
            "market_data_": {
             "symbol_": "CME:ZF%0Q",
             "type": "RawMarketData_Event"
            },
            "name": "TimeVWAPCompTheoZFMidptZN1m100vm_2658",
            "nano_vwap_length_": 60000000000,
            "ref_theo_": {
             "market_data_": {
              "symbol_": "CME:ZN%0Q",
              "type": "RawMarketData_Event"
             },
             "type": "Midpt"
            },
            "type": "TimeVWAPCompTheo",
            "vol_mult_": 1.0
           },
           "weight": 0.007658826027623614
          },
          {
           "signal": {
            "market_data_": {
             "config_": {
              "exchDt_begin": -9223372036854775808,
              "exchDt_end": 1000,
              "humanSize_": false,
              "initialQty_begin": 0,
              "initialQty_end": 2147483647,
              "qtyCap_": 2147483647,
              "receiveDt_begin": -9223372036854775808,
              "receiveDt_end": 9223372036854775807,
              "type": "SplitMarketData::Config",
              "useSplitBookInTrades": true
             },
             "symbol_": "CME:ZF%0Q",
             "type": "SplitMarketData"
            },
            "min_size_": 50,
            "name": "DurationSVZF_50c50msFast1us_8001",
            "nanos_": 50000000,
            "type": "DurationSV"
           },
           "weight": 0.00021827750452419733
          },
          {
           "signal": {
            "half_impact_size_": 1.0,
            "length_in_ticks_": 2000.0,
            "market_data_": {
             "symbol_": "CME:ZT%0Q",
             "type": "RawMarketData_Event"
            },
            "name": "SigmoidSVZT_1c2000t_8693",
            "type": "SigmoidSV"
           },
           "weight": 4.330828084805216e-05
          },
          {
           "signal": {
            "half_impact_size_": 500.0,
            "length_in_ticks_": 500.0,
            "market_data_": {
             "config_": {
              "exchDt_begin": 10000,
              "exchDt_end": 9223372036854775807,
              "humanSize_": false,
              "initialQty_begin": 0,
              "initialQty_end": 2147483647,
              "qtyCap_": 2147483647,
              "receiveDt_begin": -9223372036854775808,
              "receiveDt_end": 9223372036854775807,
              "type": "SplitMarketData::Config",
              "useSplitBookInTrades": true
             },
             "symbol_": "CME:ZF%0Q",
             "type": "SplitMarketData"
            },
            "name": "SigmoidSVZF_500c500tSlow10us_1700",
            "type": "SigmoidSV"
           },
           "weight": 9.775198180492907e-05
          },
          {
           "signal": {
            "base_theo_": {
             "fill_depth_": 4,
             "market_data_": {
              "config_": {
               "exchDt_begin": -9223372036854775808,
               "exchDt_end": 9223372036854775807,
               "humanSize_": false,
               "initialQty_begin": 0,
               "initialQty_end": 2147483647,
               "qtyCap_": 10,
               "receiveDt_begin": -9223372036854775808,
               "receiveDt_end": 9223372036854775807,
               "type": "SplitMarketData::Config",
               "useSplitBookInTrades": false
              },
              "symbol_": "CME:ZF%0Q",
              "type": "SplitMarketData"
             },
             "size_depth_": 3,
             "size_ema_length_": 100000.0,
             "size_mult_": 1.0,
             "type": "FillAve",
             "use_counts_": false
            },
            "ema_length_": 20000.0,
            "name": "TickCompTheoZFFillAveSizeZN20000t55vm_1297",
            "ref_theo_": {
             "fill_depth_": 4,
             "market_data_": {
              "config_": {
               "exchDt_begin": -9223372036854775808,
               "exchDt_end": 9223372036854775807,
               "humanSize_": false,
               "initialQty_begin": 0,
               "initialQty_end": 2147483647,
               "qtyCap_": 10,
               "receiveDt_begin": -9223372036854775808,
               "receiveDt_end": 9223372036854775807,
               "type": "SplitMarketData::Config",
               "useSplitBookInTrades": false
              },
              "symbol_": "CME:ZN%0Q",
              "type": "SplitMarketData"
             },
             "size_depth_": 3,
             "size_ema_length_": 100000.0,
             "size_mult_": 1.0,
             "type": "FillAve",
             "use_counts_": false
            },
            "type": "TickCompTheo",
            "vol_mult_": 0.5551515151515152
           },
           "weight": 0.14333789238905922
          },
          {
           "signal": {
            "market_data_": {
             "symbol_": "CME:ZF%0Q",
             "type": "RawMarketData_Event"
            },
            "min_size_": 1,
            "name": "DurationSVZF_1c1ms_1422",
            "nanos_": 1000000,
            "type": "DurationSV"
           },
           "weight": 6.164575058704638e-05
          },
          {
           "signal": {
            "half_impact_size_": 10.0,
            "length_in_ticks_": 50000.0,
            "market_data_": {
             "config_": {
              "exchDt_begin": -9223372036854775808,
              "exchDt_end": 1000,
              "humanSize_": false,
              "initialQty_begin": 0,
              "initialQty_end": 2147483647,
              "qtyCap_": 2147483647,
              "receiveDt_begin": -9223372036854775808,
              "receiveDt_end": 9223372036854775807,
              "type": "SplitMarketData::Config",
              "useSplitBookInTrades": true
             },
             "symbol_": "CME:ZF%0Q",
             "type": "SplitMarketData"
            },
            "name": "EMSSigmoidSVZF_10c50000tFast1us_1829",
            "type": "EMSSigmoidSV"
           },
           "weight": 3.833675131597638e-05
          },
          {
           "signal": {
            "half_impact_size_": 500.0,
            "length_in_ticks_": 500.0,
            "market_data_": {
             "config_": {
              "exchDt_begin": -9223372036854775808,
              "exchDt_end": 1000,
              "humanSize_": false,
              "initialQty_begin": 0,
              "initialQty_end": 2147483647,
              "qtyCap_": 2147483647,
              "receiveDt_begin": -9223372036854775808,
              "receiveDt_end": 9223372036854775807,
              "type": "SplitMarketData::Config",
              "useSplitBookInTrades": true
             },
             "symbol_": "CME:ZF%0Q",
             "type": "SplitMarketData"
            },
            "name": "SigmoidSVZF_500c500tFast1us_4861",
            "type": "SigmoidSV"
           },
           "weight": 0.0030797564656540283
          },
          {
           "signal": {
            "half_impact_size_": 1.0,
            "length_in_ticks_": 500.0,
            "market_data_": {
             "config_": {
              "exchDt_begin": 10000,
              "exchDt_end": 9223372036854775807,
              "humanSize_": false,
              "initialQty_begin": 0,
              "initialQty_end": 2147483647,
              "qtyCap_": 2147483647,
              "receiveDt_begin": -9223372036854775808,
              "receiveDt_end": 9223372036854775807,
              "type": "SplitMarketData::Config",
              "useSplitBookInTrades": true
             },
             "symbol_": "CME:ZF%0Q",
             "type": "SplitMarketData"
            },
            "name": "SigmoidSVZF_1c500tSlow10us_2697",
            "type": "SigmoidSV"
           },
           "weight": 0.00015638613204991511
          },
          {
           "signal": {
            "half_impact_size_": 500.0,
            "length_in_ticks_": 20.0,
            "market_data_": {
             "symbol_": "CME:ZF%0Q",
             "type": "RawMarketData_Event"
            },
            "name": "SigmoidSVZF_500c20t_9285",
            "type": "SigmoidSV"
           },
           "weight": 0.0006596899892819798
          }
         ]
        },
        "name": "Valuation_AeXw",
        "type": "LinearModel"
       }
      },
      "type": "MaxQSpotScorer",
      "valuation_": {
       "config_": {
        "name": "Valuation_AeXw",
        "symbol": "CME:ZF%0Q",
        "valuation": [
         {
          "signal": {
           "half_impact_size_": 500.0,
           "length_in_ticks_": 2000.0,
           "market_data_": {
            "symbol_": "CME:ZT%0Q",
            "type": "RawMarketData_Event"
           },
           "name": "SigmoidSVZT_500c2000t_4397",
           "type": "SigmoidSV"
          },
          "weight": 0.0001007627875517353
         },
         {
          "signal": {
           "fast_half_impact_size_": 100.0,
           "fast_length_in_ticks_": 10,
           "market_data_": {
            "config_": {
             "exchDt_begin": 10000,
             "exchDt_end": 9223372036854775807,
             "humanSize_": false,
             "initialQty_begin": 0,
             "initialQty_end": 2147483647,
             "qtyCap_": 2147483647,
             "receiveDt_begin": -9223372036854775808,
             "receiveDt_end": 9223372036854775807,
             "type": "SplitMarketData::Config",
             "useSplitBookInTrades": true
            },
            "symbol_": "CME:ZF%0Q",
            "type": "SplitMarketData"
           },
           "name": "PersistentSVZF_100c10t_1000c100tSlow10us_1217",
           "slow_half_impact_size_": 1000.0,
           "slow_length_in_ticks_": 100,
           "type": "PersistentSV"
          },
          "weight": 0.00017693910733932068
         },
         {
          "signal": {
           "half_impact_size_": 500.0,
           "length_in_ticks_": 2000.0,
           "market_data_": {
            "symbol_": "CME:ZN%0Q",
            "type": "RawMarketData_Event"
           },
           "name": "SigmoidSVZN_500c2000t_5560",
           "type": "SigmoidSV"
          },
          "weight": 0.000883127118472619
         },
         {
          "signal": {
           "fast_half_impact_size_": 100.0,
           "fast_length_in_ticks_": 10,
           "market_data_": {
            "config_": {
             "exchDt_begin": -9223372036854775808,
             "exchDt_end": 9223372036854775807,
             "humanSize_": false,
             "initialQty_begin": 0,
             "initialQty_end": 10,
             "qtyCap_": 2147483647,
             "receiveDt_begin": -9223372036854775808,
             "receiveDt_end": 9223372036854775807,
             "type": "SplitMarketData::Config",
             "useSplitBookInTrades": true
            },
            "symbol_": "CME:ZF%0Q",
            "type": "SplitMarketData"
           },
           "name": "PersistentSVZF_100c10t_1000c100tSmall10_5420",
           "slow_half_impact_size_": 1000.0,
           "slow_length_in_ticks_": 100,
           "type": "PersistentSV"
          },
          "weight": 0.001294890467701194
         },
         {
          "signal": {
           "fill_depth_": 2,
           "market_data_": {
            "config_": {
             "exchDt_begin": -9223372036854775808,
             "exchDt_end": 9223372036854775807,
             "humanSize_": false,
             "initialQty_begin": 0,
             "initialQty_end": 50,
             "qtyCap_": 2147483647,
             "receiveDt_begin": -9223372036854775808,
             "receiveDt_end": 9223372036854775807,
             "type": "SplitMarketData::Config",
             "useSplitBookInTrades": false
            },
            "symbol_": "CME:ZF%0Q",
            "type": "SplitMarketData"
           },
           "name": "FillAveSizeZFSmall50MD2_3908",
           "size_depth_": 2,
           "size_ema_length_": 100000.0,
           "size_mult_": 0.5,
           "type": "FillAve",
           "use_counts_": false
          },
          "weight": 0.2755638769697063
         },
         {
          "signal": {
           "fill_depth_": 2,
           "market_data_": {
            "config_": {
             "exchDt_begin": 10000,
             "exchDt_end": 9223372036854775807,
             "humanSize_": false,
             "initialQty_begin": 0,
             "initialQty_end": 50,
             "qtyCap_": 2147483647,
             "receiveDt_begin": -9223372036854775808,
             "receiveDt_end": 9223372036854775807,
             "type": "SplitMarketData::Config",
             "useSplitBookInTrades": false
            },
            "symbol_": "CME:ZF%0Q",
            "type": "SplitMarketData"
           },
           "name": "FillAveSizeZFSlow10usSmall50MD2_6624",
           "size_depth_": 2,
           "size_ema_length_": 100000.0,
           "size_mult_": 0.5,
           "type": "FillAve",
           "use_counts_": false
          },
          "weight": 0.12030426337298285
         },
         {
          "signal": {
           "fill_depth_": 2,
           "market_data_": {
            "config_": {
             "exchDt_begin": 1000000,
             "exchDt_end": 9223372036854775807,
             "humanSize_": false,
             "initialQty_begin": 10,
             "initialQty_end": 2147483647,
             "qtyCap_": 2147483647,
             "receiveDt_begin": -9223372036854775808,
             "receiveDt_end": 9223372036854775807,
             "type": "SplitMarketData::Config",
             "useSplitBookInTrades": false
            },
            "symbol_": "CME:ZF%0Q",
            "type": "SplitMarketData"
           },
           "name": "FillAveSizeZFSlow1msBig10MD2_7086",
           "size_depth_": 2,
           "size_ema_length_": 100000.0,
           "size_mult_": 0.5,
           "type": "FillAve",
           "use_counts_": false
          },
          "weight": 0.12382430439836066
         },
         {
          "signal": {
           "half_impact_size_": 1.0,
           "length_in_ticks_": 20.0,
           "market_data_": {
            "symbol_": "CME:ZN%0Q",
            "type": "RawMarketData_Event"
           },
           "name": "SigmoidSVZN_1c20t_2901",
           "type": "SigmoidSV"
          },
          "weight": 0.0004356762231873615
         },
         {
          "signal": {
           "half_impact_size1_": 30.0,
           "half_impact_size2_": 20.0,
           "length_in_ticks_": 50,
           "md1_": {
            "symbol_": "CME:ZF%0Q",
            "type": "RawMarketData_Event"
           },
           "md2_": {
            "symbol_": "CME:ZN%0Q",
            "type": "RawMarketData_Event"
           },
           "name": "ProdSVZFZN_30c50t_20c50t_5075",
           "type": "ProdSV"
          },
          "weight": 8.400126816331024e-05
         },
         {
          "signal": {
           "base_theo_": {
            "fill_depth_": 4,
            "market_data_": {
             "config_": {
              "exchDt_begin": -9223372036854775808,
              "exchDt_end": 9223372036854775807,
              "humanSize_": false,
              "initialQty_begin": 0,
              "initialQty_end": 2147483647,
              "qtyCap_": 10,
              "receiveDt_begin": -9223372036854775808,
              "receiveDt_end": 9223372036854775807,
              "type": "SplitMarketData::Config",
              "useSplitBookInTrades": false
             },
             "symbol_": "CME:ZF%0Q",
             "type": "SplitMarketData"
            },
            "size_depth_": 3,
            "size_ema_length_": 100000.0,
            "size_mult_": 1.0,
            "type": "FillAve",
            "use_counts_": false
           },
           "intensity_mult_": 10000.0,
           "long_decay_": 600000000000,
           "name": "TICTZFFillAveSizeZN10m10ms10000t55vm_1348",
           "ref_theo_": {
            "fill_depth_": 4,
            "market_data_": {
             "config_": {
              "exchDt_begin": -9223372036854775808,
              "exchDt_end": 9223372036854775807,
              "humanSize_": false,
              "initialQty_begin": 0,
              "initialQty_end": 2147483647,
              "qtyCap_": 10,
              "receiveDt_begin": -9223372036854775808,
              "receiveDt_end": 9223372036854775807,
              "type": "SplitMarketData::Config",
              "useSplitBookInTrades": false
             },
             "symbol_": "CME:ZN%0Q",
             "type": "SplitMarketData"
            },
            "size_depth_": 3,
            "size_ema_length_": 100000.0,
            "size_mult_": 1.0,
            "type": "FillAve",
            "use_counts_": false
           },
           "short_decay_": 10000000,
           "type": "TradeIntensityCompTheo",
           "vol_mult_": 0.5551515151515152
          },
          "weight": 0.06232185720271092
         },
         {
          "signal": {
           "base_theo_": {
            "fill_depth_": 4,
            "market_data_": {
             "config_": {
              "exchDt_begin": -9223372036854775808,
              "exchDt_end": 9223372036854775807,
              "humanSize_": false,
              "initialQty_begin": 0,
              "initialQty_end": 2147483647,
              "qtyCap_": 10,
              "receiveDt_begin": -9223372036854775808,
              "receiveDt_end": 9223372036854775807,
              "type": "SplitMarketData::Config",
              "useSplitBookInTrades": false
             },
             "symbol_": "CME:ZF%0Q",
             "type": "SplitMarketData"
            },
            "size_depth_": 3,
            "size_ema_length_": 100000.0,
            "size_mult_": 1.0,
            "type": "FillAve",
            "use_counts_": false
           },
           "ema_length_": 600000000000,
           "name": "TimeCompTheoZFFillAveSizeZT10m244vm_1653",
           "ref_theo_": {
            "fill_depth_": 4,
            "market_data_": {
             "config_": {
              "exchDt_begin": -9223372036854775808,
              "exchDt_end": 9223372036854775807,
              "humanSize_": false,
              "initialQty_begin": 0,
              "initialQty_end": 2147483647,
              "qtyCap_": 10,
              "receiveDt_begin": -9223372036854775808,
              "receiveDt_end": 9223372036854775807,
              "type": "SplitMarketData::Config",
              "useSplitBookInTrades": false
             },
             "symbol_": "CME:ZT%0Q",
             "type": "SplitMarketData"
            },
            "size_depth_": 3,
            "size_ema_length_": 100000.0,
            "size_mult_": 1.0,
            "type": "FillAve",
            "use_counts_": false
           },
           "type": "TimeCompTheo",
           "vol_mult_": 2.4426666666666668
          },
          "weight": 0.014834781948862237
         },
         {
          "signal": {
           "base_theo_": {
            "fill_depth_": 4,
            "market_data_": {
             "config_": {
              "exchDt_begin": -9223372036854775808,
              "exchDt_end": 9223372036854775807,
              "humanSize_": false,
              "initialQty_begin": 0,
              "initialQty_end": 2147483647,
              "qtyCap_": 10,
              "receiveDt_begin": -9223372036854775808,
              "receiveDt_end": 9223372036854775807,
              "type": "SplitMarketData::Config",
              "useSplitBookInTrades": false
             },
             "symbol_": "CME:ZF%0Q",
             "type": "SplitMarketData"
            },
            "size_depth_": 3,
            "size_ema_length_": 100000.0,
            "size_mult_": 1.0,
            "type": "FillAve",
            "use_counts_": false
           },
           "intensity_mult_": 10000.0,
           "long_decay_": 600000000000,
           "name": "TICTZFFillAveSizeZT10m10s10000t244vm_1336",
           "ref_theo_": {
            "fill_depth_": 4,
            "market_data_": {
             "config_": {
              "exchDt_begin": -9223372036854775808,
              "exchDt_end": 9223372036854775807,
              "humanSize_": false,
              "initialQty_begin": 0,
              "initialQty_end": 2147483647,
              "qtyCap_": 10,
              "receiveDt_begin": -9223372036854775808,
              "receiveDt_end": 9223372036854775807,
              "type": "SplitMarketData::Config",
              "useSplitBookInTrades": false
             },
             "symbol_": "CME:ZT%0Q",
             "type": "SplitMarketData"
            },
            "size_depth_": 3,
            "size_ema_length_": 100000.0,
            "size_mult_": 1.0,
            "type": "FillAve",
            "use_counts_": false
           },
           "short_decay_": 10000000000,
           "type": "TradeIntensityCompTheo",
           "vol_mult_": 2.4426666666666668
          },
          "weight": 0.09821639797430351
         },
         {
          "signal": {
           "market_data_": {
            "symbol_": "CME:ZF%0Q",
            "type": "RawMarketData_Event"
           },
           "name": "TimeVWAPCompTheoZFMidptZN10ms100vm_1428",
           "nano_vwap_length_": 10000000,
           "ref_theo_": {
            "market_data_": {
             "symbol_": "CME:ZN%0Q",
             "type": "RawMarketData_Event"
            },
            "type": "Midpt"
           },
           "type": "TimeVWAPCompTheo",
           "vol_mult_": 1.0
          },
          "weight": 0.011877958473329094
         },
         {
          "signal": {
           "fill_depth_": 2,
           "market_data_": {
            "symbol_": "CME:ZF%0Q",
            "type": "IcebergTotalRefresh"
           },
           "name": "FillAveSizeZFIcebergRefreshMD3_8128",
           "size_depth_": 3,
           "size_ema_length_": 100000.0,
           "size_mult_": 1.0,
           "type": "FillAve",
           "use_counts_": false
          },
          "weight": 0.041298804587319604
         },
         {
          "signal": {
           "market_data_": {
            "config_": {
             "exchDt_begin": 10000,
             "exchDt_end": 9223372036854775807,
             "humanSize_": false,
             "initialQty_begin": 0,
             "initialQty_end": 2147483647,
             "qtyCap_": 2147483647,
             "receiveDt_begin": -9223372036854775808,
             "receiveDt_end": 9223372036854775807,
             "type": "SplitMarketData::Config",
             "useSplitBookInTrades": true
            },
            "symbol_": "CME:ZF%0Q",
            "type": "SplitMarketData"
           },
           "min_size_": 1,
           "name": "DurationSVZF_1c1msSlow10us_3868",
           "nanos_": 1000000,
           "type": "DurationSV"
          },
          "weight": 9.786430465597851e-05
         },
         {
          "signal": {
           "fill_depth_": 2,
           "market_data_": {
            "config_": {
             "exchDt_begin": -9223372036854775808,
             "exchDt_end": 9223372036854775807,
             "humanSize_": true,
             "initialQty_begin": 0,
             "initialQty_end": 2147483647,
             "qtyCap_": 2147483647,
             "receiveDt_begin": -9223372036854775808,
             "receiveDt_end": 9223372036854775807,
             "type": "SplitMarketData::Config",
             "useSplitBookInTrades": true
            },
            "symbol_": "CME:ZF%0Q",
            "type": "SplitMarketData"
           },
           "name": "FillAveSizeZFHumanSizeMD2_5400",
           "size_depth_": 2,
           "size_ema_length_": 100000.0,
           "size_mult_": 0.5,
           "type": "FillAve",
           "use_counts_": false
          },
          "weight": 0.10076216309126965
         },
         {
          "signal": {
           "market_data_": {
            "config_": {
             "exchDt_begin": -9223372036854775808,
             "exchDt_end": 9223372036854775807,
             "humanSize_": true,
             "initialQty_begin": 0,
             "initialQty_end": 2147483647,
             "qtyCap_": 2147483647,
             "receiveDt_begin": -9223372036854775808,
             "receiveDt_end": 9223372036854775807,
             "type": "SplitMarketData::Config",
             "useSplitBookInTrades": true
            },
            "symbol_": "CME:ZF%0Q",
            "type": "SplitMarketData"
           },
           "min_size_": 1,
           "name": "DurationSVZF_1c1msHuman_5936",
           "nanos_": 1000000,
           "type": "DurationSV"
          },
          "weight": 8.372296697687381e-05
         },
         {
          "signal": {
           "market_data_": {
            "symbol_": "CME:ZF%0Q",
            "type": "RawMarketData_Event"
           },
           "name": "TimeVWAPCompTheoZFMidptZN1m100vm_2658",
           "nano_vwap_length_": 60000000000,
           "ref_theo_": {
            "market_data_": {
             "symbol_": "CME:ZN%0Q",
             "type": "RawMarketData_Event"
            },
            "type": "Midpt"
           },
           "type": "TimeVWAPCompTheo",
           "vol_mult_": 1.0
          },
          "weight": 0.007658826027623614
         },
         {
          "signal": {
           "market_data_": {
            "config_": {
             "exchDt_begin": -9223372036854775808,
             "exchDt_end": 1000,
             "humanSize_": false,
             "initialQty_begin": 0,
             "initialQty_end": 2147483647,
             "qtyCap_": 2147483647,
             "receiveDt_begin": -9223372036854775808,
             "receiveDt_end": 9223372036854775807,
             "type": "SplitMarketData::Config",
             "useSplitBookInTrades": true
            },
            "symbol_": "CME:ZF%0Q",
            "type": "SplitMarketData"
           },
           "min_size_": 50,
           "name": "DurationSVZF_50c50msFast1us_8001",
           "nanos_": 50000000,
           "type": "DurationSV"
          },
          "weight": 0.00021827750452419733
         },
         {
          "signal": {
           "half_impact_size_": 1.0,
           "length_in_ticks_": 2000.0,
           "market_data_": {
            "symbol_": "CME:ZT%0Q",
            "type": "RawMarketData_Event"
           },
           "name": "SigmoidSVZT_1c2000t_8693",
           "type": "SigmoidSV"
          },
          "weight": 4.330828084805216e-05
         },
         {
          "signal": {
           "half_impact_size_": 500.0,
           "length_in_ticks_": 500.0,
           "market_data_": {
            "config_": {
             "exchDt_begin": 10000,
             "exchDt_end": 9223372036854775807,
             "humanSize_": false,
             "initialQty_begin": 0,
             "initialQty_end": 2147483647,
             "qtyCap_": 2147483647,
             "receiveDt_begin": -9223372036854775808,
             "receiveDt_end": 9223372036854775807,
             "type": "SplitMarketData::Config",
             "useSplitBookInTrades": true
            },
            "symbol_": "CME:ZF%0Q",
            "type": "SplitMarketData"
           },
           "name": "SigmoidSVZF_500c500tSlow10us_1700",
           "type": "SigmoidSV"
          },
          "weight": 9.775198180492907e-05
         },
         {
          "signal": {
           "base_theo_": {
            "fill_depth_": 4,
            "market_data_": {
             "config_": {
              "exchDt_begin": -9223372036854775808,
              "exchDt_end": 9223372036854775807,
              "humanSize_": false,
              "initialQty_begin": 0,
              "initialQty_end": 2147483647,
              "qtyCap_": 10,
              "receiveDt_begin": -9223372036854775808,
              "receiveDt_end": 9223372036854775807,
              "type": "SplitMarketData::Config",
              "useSplitBookInTrades": false
             },
             "symbol_": "CME:ZF%0Q",
             "type": "SplitMarketData"
            },
            "size_depth_": 3,
            "size_ema_length_": 100000.0,
            "size_mult_": 1.0,
            "type": "FillAve",
            "use_counts_": false
           },
           "ema_length_": 20000.0,
           "name": "TickCompTheoZFFillAveSizeZN20000t55vm_1297",
           "ref_theo_": {
            "fill_depth_": 4,
            "market_data_": {
             "config_": {
              "exchDt_begin": -9223372036854775808,
              "exchDt_end": 9223372036854775807,
              "humanSize_": false,
              "initialQty_begin": 0,
              "initialQty_end": 2147483647,
              "qtyCap_": 10,
              "receiveDt_begin": -9223372036854775808,
              "receiveDt_end": 9223372036854775807,
              "type": "SplitMarketData::Config",
              "useSplitBookInTrades": false
             },
             "symbol_": "CME:ZN%0Q",
             "type": "SplitMarketData"
            },
            "size_depth_": 3,
            "size_ema_length_": 100000.0,
            "size_mult_": 1.0,
            "type": "FillAve",
            "use_counts_": false
           },
           "type": "TickCompTheo",
           "vol_mult_": 0.5551515151515152
          },
          "weight": 0.14333789238905922
         },
         {
          "signal": {
           "market_data_": {
            "symbol_": "CME:ZF%0Q",
            "type": "RawMarketData_Event"
           },
           "min_size_": 1,
           "name": "DurationSVZF_1c1ms_1422",
           "nanos_": 1000000,
           "type": "DurationSV"
          },
          "weight": 6.164575058704638e-05
         },
         {
          "signal": {
           "half_impact_size_": 10.0,
           "length_in_ticks_": 50000.0,
           "market_data_": {
            "config_": {
             "exchDt_begin": -9223372036854775808,
             "exchDt_end": 1000,
             "humanSize_": false,
             "initialQty_begin": 0,
             "initialQty_end": 2147483647,
             "qtyCap_": 2147483647,
             "receiveDt_begin": -9223372036854775808,
             "receiveDt_end": 9223372036854775807,
             "type": "SplitMarketData::Config",
             "useSplitBookInTrades": true
            },
            "symbol_": "CME:ZF%0Q",
            "type": "SplitMarketData"
           },
           "name": "EMSSigmoidSVZF_10c50000tFast1us_1829",
           "type": "EMSSigmoidSV"
          },
          "weight": 3.833675131597638e-05
         },
         {
          "signal": {
           "half_impact_size_": 500.0,
           "length_in_ticks_": 500.0,
           "market_data_": {
            "config_": {
             "exchDt_begin": -9223372036854775808,
             "exchDt_end": 1000,
             "humanSize_": false,
             "initialQty_begin": 0,
             "initialQty_end": 2147483647,
             "qtyCap_": 2147483647,
             "receiveDt_begin": -9223372036854775808,
             "receiveDt_end": 9223372036854775807,
             "type": "SplitMarketData::Config",
             "useSplitBookInTrades": true
            },
            "symbol_": "CME:ZF%0Q",
            "type": "SplitMarketData"
           },
           "name": "SigmoidSVZF_500c500tFast1us_4861",
           "type": "SigmoidSV"
          },
          "weight": 0.0030797564656540283
         },
         {
          "signal": {
           "half_impact_size_": 1.0,
           "length_in_ticks_": 500.0,
           "market_data_": {
            "config_": {
             "exchDt_begin": 10000,
             "exchDt_end": 9223372036854775807,
             "humanSize_": false,
             "initialQty_begin": 0,
             "initialQty_end": 2147483647,
             "qtyCap_": 2147483647,
             "receiveDt_begin": -9223372036854775808,
             "receiveDt_end": 9223372036854775807,
             "type": "SplitMarketData::Config",
             "useSplitBookInTrades": true
            },
            "symbol_": "CME:ZF%0Q",
            "type": "SplitMarketData"
           },
           "name": "SigmoidSVZF_1c500tSlow10us_2697",
           "type": "SigmoidSV"
          },
          "weight": 0.00015638613204991511
         },
         {
          "signal": {
           "half_impact_size_": 500.0,
           "length_in_ticks_": 20.0,
           "market_data_": {
            "symbol_": "CME:ZF%0Q",
            "type": "RawMarketData_Event"
           },
           "name": "SigmoidSVZF_500c20t_9285",
           "type": "SigmoidSV"
          },
          "weight": 0.0006596899892819798
         }
        ]
       },
       "name": "Valuation_AeXw",
       "type": "LinearModel"
      }
     },
     "symbol": "CME:ZF%0Q",
     "type": "BasicMaker",
     "valuation": {
      "config_": {
       "name": "Valuation_AeXw",
       "symbol": "CME:ZF%0Q",
       "valuation": [
        {
         "signal": {
          "half_impact_size_": 500.0,
          "length_in_ticks_": 2000.0,
          "market_data_": {
           "symbol_": "CME:ZT%0Q",
           "type": "RawMarketData_Event"
          },
          "name": "SigmoidSVZT_500c2000t_4397",
          "type": "SigmoidSV"
         },
         "weight": 0.0001007627875517353
        },
        {
         "signal": {
          "fast_half_impact_size_": 100.0,
          "fast_length_in_ticks_": 10,
          "market_data_": {
           "config_": {
            "exchDt_begin": 10000,
            "exchDt_end": 9223372036854775807,
            "humanSize_": false,
            "initialQty_begin": 0,
            "initialQty_end": 2147483647,
            "qtyCap_": 2147483647,
            "receiveDt_begin": -9223372036854775808,
            "receiveDt_end": 9223372036854775807,
            "type": "SplitMarketData::Config",
            "useSplitBookInTrades": true
           },
           "symbol_": "CME:ZF%0Q",
           "type": "SplitMarketData"
          },
          "name": "PersistentSVZF_100c10t_1000c100tSlow10us_1217",
          "slow_half_impact_size_": 1000.0,
          "slow_length_in_ticks_": 100,
          "type": "PersistentSV"
         },
         "weight": 0.00017693910733932068
        },
        {
         "signal": {
          "half_impact_size_": 500.0,
          "length_in_ticks_": 2000.0,
          "market_data_": {
           "symbol_": "CME:ZN%0Q",
           "type": "RawMarketData_Event"
          },
          "name": "SigmoidSVZN_500c2000t_5560",
          "type": "SigmoidSV"
         },
         "weight": 0.000883127118472619
        },
        {
         "signal": {
          "fast_half_impact_size_": 100.0,
          "fast_length_in_ticks_": 10,
          "market_data_": {
           "config_": {
            "exchDt_begin": -9223372036854775808,
            "exchDt_end": 9223372036854775807,
            "humanSize_": false,
            "initialQty_begin": 0,
            "initialQty_end": 10,
            "qtyCap_": 2147483647,
            "receiveDt_begin": -9223372036854775808,
            "receiveDt_end": 9223372036854775807,
            "type": "SplitMarketData::Config",
            "useSplitBookInTrades": true
           },
           "symbol_": "CME:ZF%0Q",
           "type": "SplitMarketData"
          },
          "name": "PersistentSVZF_100c10t_1000c100tSmall10_5420",
          "slow_half_impact_size_": 1000.0,
          "slow_length_in_ticks_": 100,
          "type": "PersistentSV"
         },
         "weight": 0.001294890467701194
        },
        {
         "signal": {
          "fill_depth_": 2,
          "market_data_": {
           "config_": {
            "exchDt_begin": -9223372036854775808,
            "exchDt_end": 9223372036854775807,
            "humanSize_": false,
            "initialQty_begin": 0,
            "initialQty_end": 50,
            "qtyCap_": 2147483647,
            "receiveDt_begin": -9223372036854775808,
            "receiveDt_end": 9223372036854775807,
            "type": "SplitMarketData::Config",
            "useSplitBookInTrades": false
           },
           "symbol_": "CME:ZF%0Q",
           "type": "SplitMarketData"
          },
          "name": "FillAveSizeZFSmall50MD2_3908",
          "size_depth_": 2,
          "size_ema_length_": 100000.0,
          "size_mult_": 0.5,
          "type": "FillAve",
          "use_counts_": false
         },
         "weight": 0.2755638769697063
        },
        {
         "signal": {
          "fill_depth_": 2,
          "market_data_": {
           "config_": {
            "exchDt_begin": 10000,
            "exchDt_end": 9223372036854775807,
            "humanSize_": false,
            "initialQty_begin": 0,
            "initialQty_end": 50,
            "qtyCap_": 2147483647,
            "receiveDt_begin": -9223372036854775808,
            "receiveDt_end": 9223372036854775807,
            "type": "SplitMarketData::Config",
            "useSplitBookInTrades": false
           },
           "symbol_": "CME:ZF%0Q",
           "type": "SplitMarketData"
          },
          "name": "FillAveSizeZFSlow10usSmall50MD2_6624",
          "size_depth_": 2,
          "size_ema_length_": 100000.0,
          "size_mult_": 0.5,
          "type": "FillAve",
          "use_counts_": false
         },
         "weight": 0.12030426337298285
        },
        {
         "signal": {
          "fill_depth_": 2,
          "market_data_": {
           "config_": {
            "exchDt_begin": 1000000,
            "exchDt_end": 9223372036854775807,
            "humanSize_": false,
            "initialQty_begin": 10,
            "initialQty_end": 2147483647,
            "qtyCap_": 2147483647,
            "receiveDt_begin": -9223372036854775808,
            "receiveDt_end": 9223372036854775807,
            "type": "SplitMarketData::Config",
            "useSplitBookInTrades": false
           },
           "symbol_": "CME:ZF%0Q",
           "type": "SplitMarketData"
          },
          "name": "FillAveSizeZFSlow1msBig10MD2_7086",
          "size_depth_": 2,
          "size_ema_length_": 100000.0,
          "size_mult_": 0.5,
          "type": "FillAve",
          "use_counts_": false
         },
         "weight": 0.12382430439836066
        },
        {
         "signal": {
          "half_impact_size_": 1.0,
          "length_in_ticks_": 20.0,
          "market_data_": {
           "symbol_": "CME:ZN%0Q",
           "type": "RawMarketData_Event"
          },
          "name": "SigmoidSVZN_1c20t_2901",
          "type": "SigmoidSV"
         },
         "weight": 0.0004356762231873615
        },
        {
         "signal": {
          "half_impact_size1_": 30.0,
          "half_impact_size2_": 20.0,
          "length_in_ticks_": 50,
          "md1_": {
           "symbol_": "CME:ZF%0Q",
           "type": "RawMarketData_Event"
          },
          "md2_": {
           "symbol_": "CME:ZN%0Q",
           "type": "RawMarketData_Event"
          },
          "name": "ProdSVZFZN_30c50t_20c50t_5075",
          "type": "ProdSV"
         },
         "weight": 8.400126816331024e-05
        },
        {
         "signal": {
          "base_theo_": {
           "fill_depth_": 4,
           "market_data_": {
            "config_": {
             "exchDt_begin": -9223372036854775808,
             "exchDt_end": 9223372036854775807,
             "humanSize_": false,
             "initialQty_begin": 0,
             "initialQty_end": 2147483647,
             "qtyCap_": 10,
             "receiveDt_begin": -9223372036854775808,
             "receiveDt_end": 9223372036854775807,
             "type": "SplitMarketData::Config",
             "useSplitBookInTrades": false
            },
            "symbol_": "CME:ZF%0Q",
            "type": "SplitMarketData"
           },
           "size_depth_": 3,
           "size_ema_length_": 100000.0,
           "size_mult_": 1.0,
           "type": "FillAve",
           "use_counts_": false
          },
          "intensity_mult_": 10000.0,
          "long_decay_": 600000000000,
          "name": "TICTZFFillAveSizeZN10m10ms10000t55vm_1348",
          "ref_theo_": {
           "fill_depth_": 4,
           "market_data_": {
            "config_": {
             "exchDt_begin": -9223372036854775808,
             "exchDt_end": 9223372036854775807,
             "humanSize_": false,
             "initialQty_begin": 0,
             "initialQty_end": 2147483647,
             "qtyCap_": 10,
             "receiveDt_begin": -9223372036854775808,
             "receiveDt_end": 9223372036854775807,
             "type": "SplitMarketData::Config",
             "useSplitBookInTrades": false
            },
            "symbol_": "CME:ZN%0Q",
            "type": "SplitMarketData"
           },
           "size_depth_": 3,
           "size_ema_length_": 100000.0,
           "size_mult_": 1.0,
           "type": "FillAve",
           "use_counts_": false
          },
          "short_decay_": 10000000,
          "type": "TradeIntensityCompTheo",
          "vol_mult_": 0.5551515151515152
         },
         "weight": 0.06232185720271092
        },
        {
         "signal": {
          "base_theo_": {
           "fill_depth_": 4,
           "market_data_": {
            "config_": {
             "exchDt_begin": -9223372036854775808,
             "exchDt_end": 9223372036854775807,
             "humanSize_": false,
             "initialQty_begin": 0,
             "initialQty_end": 2147483647,
             "qtyCap_": 10,
             "receiveDt_begin": -9223372036854775808,
             "receiveDt_end": 9223372036854775807,
             "type": "SplitMarketData::Config",
             "useSplitBookInTrades": false
            },
            "symbol_": "CME:ZF%0Q",
            "type": "SplitMarketData"
           },
           "size_depth_": 3,
           "size_ema_length_": 100000.0,
           "size_mult_": 1.0,
           "type": "FillAve",
           "use_counts_": false
          },
          "ema_length_": 600000000000,
          "name": "TimeCompTheoZFFillAveSizeZT10m244vm_1653",
          "ref_theo_": {
           "fill_depth_": 4,
           "market_data_": {
            "config_": {
             "exchDt_begin": -9223372036854775808,
             "exchDt_end": 9223372036854775807,
             "humanSize_": false,
             "initialQty_begin": 0,
             "initialQty_end": 2147483647,
             "qtyCap_": 10,
             "receiveDt_begin": -9223372036854775808,
             "receiveDt_end": 9223372036854775807,
             "type": "SplitMarketData::Config",
             "useSplitBookInTrades": false
            },
            "symbol_": "CME:ZT%0Q",
            "type": "SplitMarketData"
           },
           "size_depth_": 3,
           "size_ema_length_": 100000.0,
           "size_mult_": 1.0,
           "type": "FillAve",
           "use_counts_": false
          },
          "type": "TimeCompTheo",
          "vol_mult_": 2.4426666666666668
         },
         "weight": 0.014834781948862237
        },
        {
         "signal": {
          "base_theo_": {
           "fill_depth_": 4,
           "market_data_": {
            "config_": {
             "exchDt_begin": -9223372036854775808,
             "exchDt_end": 9223372036854775807,
             "humanSize_": false,
             "initialQty_begin": 0,
             "initialQty_end": 2147483647,
             "qtyCap_": 10,
             "receiveDt_begin": -9223372036854775808,
             "receiveDt_end": 9223372036854775807,
             "type": "SplitMarketData::Config",
             "useSplitBookInTrades": false
            },
            "symbol_": "CME:ZF%0Q",
            "type": "SplitMarketData"
           },
           "size_depth_": 3,
           "size_ema_length_": 100000.0,
           "size_mult_": 1.0,
           "type": "FillAve",
           "use_counts_": false
          },
          "intensity_mult_": 10000.0,
          "long_decay_": 600000000000,
          "name": "TICTZFFillAveSizeZT10m10s10000t244vm_1336",
          "ref_theo_": {
           "fill_depth_": 4,
           "market_data_": {
            "config_": {
             "exchDt_begin": -9223372036854775808,
             "exchDt_end": 9223372036854775807,
             "humanSize_": false,
             "initialQty_begin": 0,
             "initialQty_end": 2147483647,
             "qtyCap_": 10,
             "receiveDt_begin": -9223372036854775808,
             "receiveDt_end": 9223372036854775807,
             "type": "SplitMarketData::Config",
             "useSplitBookInTrades": false
            },
            "symbol_": "CME:ZT%0Q",
            "type": "SplitMarketData"
           },
           "size_depth_": 3,
           "size_ema_length_": 100000.0,
           "size_mult_": 1.0,
           "type": "FillAve",
           "use_counts_": false
          },
          "short_decay_": 10000000000,
          "type": "TradeIntensityCompTheo",
          "vol_mult_": 2.4426666666666668
         },
         "weight": 0.09821639797430351
        },
        {
         "signal": {
          "market_data_": {
           "symbol_": "CME:ZF%0Q",
           "type": "RawMarketData_Event"
          },
          "name": "TimeVWAPCompTheoZFMidptZN10ms100vm_1428",
          "nano_vwap_length_": 10000000,
          "ref_theo_": {
           "market_data_": {
            "symbol_": "CME:ZN%0Q",
            "type": "RawMarketData_Event"
           },
           "type": "Midpt"
          },
          "type": "TimeVWAPCompTheo",
          "vol_mult_": 1.0
         },
         "weight": 0.011877958473329094
        },
        {
         "signal": {
          "fill_depth_": 2,
          "market_data_": {
           "symbol_": "CME:ZF%0Q",
           "type": "IcebergTotalRefresh"
          },
          "name": "FillAveSizeZFIcebergRefreshMD3_8128",
          "size_depth_": 3,
          "size_ema_length_": 100000.0,
          "size_mult_": 1.0,
          "type": "FillAve",
          "use_counts_": false
         },
         "weight": 0.041298804587319604
        },
        {
         "signal": {
          "market_data_": {
           "config_": {
            "exchDt_begin": 10000,
            "exchDt_end": 9223372036854775807,
            "humanSize_": false,
            "initialQty_begin": 0,
            "initialQty_end": 2147483647,
            "qtyCap_": 2147483647,
            "receiveDt_begin": -9223372036854775808,
            "receiveDt_end": 9223372036854775807,
            "type": "SplitMarketData::Config",
            "useSplitBookInTrades": true
           },
           "symbol_": "CME:ZF%0Q",
           "type": "SplitMarketData"
          },
          "min_size_": 1,
          "name": "DurationSVZF_1c1msSlow10us_3868",
          "nanos_": 1000000,
          "type": "DurationSV"
         },
         "weight": 9.786430465597851e-05
        },
        {
         "signal": {
          "fill_depth_": 2,
          "market_data_": {
           "config_": {
            "exchDt_begin": -9223372036854775808,
            "exchDt_end": 9223372036854775807,
            "humanSize_": true,
            "initialQty_begin": 0,
            "initialQty_end": 2147483647,
            "qtyCap_": 2147483647,
            "receiveDt_begin": -9223372036854775808,
            "receiveDt_end": 9223372036854775807,
            "type": "SplitMarketData::Config",
            "useSplitBookInTrades": true
           },
           "symbol_": "CME:ZF%0Q",
           "type": "SplitMarketData"
          },
          "name": "FillAveSizeZFHumanSizeMD2_5400",
          "size_depth_": 2,
          "size_ema_length_": 100000.0,
          "size_mult_": 0.5,
          "type": "FillAve",
          "use_counts_": false
         },
         "weight": 0.10076216309126965
        },
        {
         "signal": {
          "market_data_": {
           "config_": {
            "exchDt_begin": -9223372036854775808,
            "exchDt_end": 9223372036854775807,
            "humanSize_": true,
            "initialQty_begin": 0,
            "initialQty_end": 2147483647,
            "qtyCap_": 2147483647,
            "receiveDt_begin": -9223372036854775808,
            "receiveDt_end": 9223372036854775807,
            "type": "SplitMarketData::Config",
            "useSplitBookInTrades": true
           },
           "symbol_": "CME:ZF%0Q",
           "type": "SplitMarketData"
          },
          "min_size_": 1,
          "name": "DurationSVZF_1c1msHuman_5936",
          "nanos_": 1000000,
          "type": "DurationSV"
         },
         "weight": 8.372296697687381e-05
        },
        {
         "signal": {
          "market_data_": {
           "symbol_": "CME:ZF%0Q",
           "type": "RawMarketData_Event"
          },
          "name": "TimeVWAPCompTheoZFMidptZN1m100vm_2658",
          "nano_vwap_length_": 60000000000,
          "ref_theo_": {
           "market_data_": {
            "symbol_": "CME:ZN%0Q",
            "type": "RawMarketData_Event"
           },
           "type": "Midpt"
          },
          "type": "TimeVWAPCompTheo",
          "vol_mult_": 1.0
         },
         "weight": 0.007658826027623614
        },
        {
         "signal": {
          "market_data_": {
           "config_": {
            "exchDt_begin": -9223372036854775808,
            "exchDt_end": 1000,
            "humanSize_": false,
            "initialQty_begin": 0,
            "initialQty_end": 2147483647,
            "qtyCap_": 2147483647,
            "receiveDt_begin": -9223372036854775808,
            "receiveDt_end": 9223372036854775807,
            "type": "SplitMarketData::Config",
            "useSplitBookInTrades": true
           },
           "symbol_": "CME:ZF%0Q",
           "type": "SplitMarketData"
          },
          "min_size_": 50,
          "name": "DurationSVZF_50c50msFast1us_8001",
          "nanos_": 50000000,
          "type": "DurationSV"
         },
         "weight": 0.00021827750452419733
        },
        {
         "signal": {
          "half_impact_size_": 1.0,
          "length_in_ticks_": 2000.0,
          "market_data_": {
           "symbol_": "CME:ZT%0Q",
           "type": "RawMarketData_Event"
          },
          "name": "SigmoidSVZT_1c2000t_8693",
          "type": "SigmoidSV"
         },
         "weight": 4.330828084805216e-05
        },
        {
         "signal": {
          "half_impact_size_": 500.0,
          "length_in_ticks_": 500.0,
          "market_data_": {
           "config_": {
            "exchDt_begin": 10000,
            "exchDt_end": 9223372036854775807,
            "humanSize_": false,
            "initialQty_begin": 0,
            "initialQty_end": 2147483647,
            "qtyCap_": 2147483647,
            "receiveDt_begin": -9223372036854775808,
            "receiveDt_end": 9223372036854775807,
            "type": "SplitMarketData::Config",
            "useSplitBookInTrades": true
           },
           "symbol_": "CME:ZF%0Q",
           "type": "SplitMarketData"
          },
          "name": "SigmoidSVZF_500c500tSlow10us_1700",
          "type": "SigmoidSV"
         },
         "weight": 9.775198180492907e-05
        },
        {
         "signal": {
          "base_theo_": {
           "fill_depth_": 4,
           "market_data_": {
            "config_": {
             "exchDt_begin": -9223372036854775808,
             "exchDt_end": 9223372036854775807,
             "humanSize_": false,
             "initialQty_begin": 0,
             "initialQty_end": 2147483647,
             "qtyCap_": 10,
             "receiveDt_begin": -9223372036854775808,
             "receiveDt_end": 9223372036854775807,
             "type": "SplitMarketData::Config",
             "useSplitBookInTrades": false
            },
            "symbol_": "CME:ZF%0Q",
            "type": "SplitMarketData"
           },
           "size_depth_": 3,
           "size_ema_length_": 100000.0,
           "size_mult_": 1.0,
           "type": "FillAve",
           "use_counts_": false
          },
          "ema_length_": 20000.0,
          "name": "TickCompTheoZFFillAveSizeZN20000t55vm_1297",
          "ref_theo_": {
           "fill_depth_": 4,
           "market_data_": {
            "config_": {
             "exchDt_begin": -9223372036854775808,
             "exchDt_end": 9223372036854775807,
             "humanSize_": false,
             "initialQty_begin": 0,
             "initialQty_end": 2147483647,
             "qtyCap_": 10,
             "receiveDt_begin": -9223372036854775808,
             "receiveDt_end": 9223372036854775807,
             "type": "SplitMarketData::Config",
             "useSplitBookInTrades": false
            },
            "symbol_": "CME:ZN%0Q",
            "type": "SplitMarketData"
           },
           "size_depth_": 3,
           "size_ema_length_": 100000.0,
           "size_mult_": 1.0,
           "type": "FillAve",
           "use_counts_": false
          },
          "type": "TickCompTheo",
          "vol_mult_": 0.5551515151515152
         },
         "weight": 0.14333789238905922
        },
        {
         "signal": {
          "market_data_": {
           "symbol_": "CME:ZF%0Q",
           "type": "RawMarketData_Event"
          },
          "min_size_": 1,
          "name": "DurationSVZF_1c1ms_1422",
          "nanos_": 1000000,
          "type": "DurationSV"
         },
         "weight": 6.164575058704638e-05
        },
        {
         "signal": {
          "half_impact_size_": 10.0,
          "length_in_ticks_": 50000.0,
          "market_data_": {
           "config_": {
            "exchDt_begin": -9223372036854775808,
            "exchDt_end": 1000,
            "humanSize_": false,
            "initialQty_begin": 0,
            "initialQty_end": 2147483647,
            "qtyCap_": 2147483647,
            "receiveDt_begin": -9223372036854775808,
            "receiveDt_end": 9223372036854775807,
            "type": "SplitMarketData::Config",
            "useSplitBookInTrades": true
           },
           "symbol_": "CME:ZF%0Q",
           "type": "SplitMarketData"
          },
          "name": "EMSSigmoidSVZF_10c50000tFast1us_1829",
          "type": "EMSSigmoidSV"
         },
         "weight": 3.833675131597638e-05
        },
        {
         "signal": {
          "half_impact_size_": 500.0,
          "length_in_ticks_": 500.0,
          "market_data_": {
           "config_": {
            "exchDt_begin": -9223372036854775808,
            "exchDt_end": 1000,
            "humanSize_": false,
            "initialQty_begin": 0,
            "initialQty_end": 2147483647,
            "qtyCap_": 2147483647,
            "receiveDt_begin": -9223372036854775808,
            "receiveDt_end": 9223372036854775807,
            "type": "SplitMarketData::Config",
            "useSplitBookInTrades": true
           },
           "symbol_": "CME:ZF%0Q",
           "type": "SplitMarketData"
          },
          "name": "SigmoidSVZF_500c500tFast1us_4861",
          "type": "SigmoidSV"
         },
         "weight": 0.0030797564656540283
        },
        {
         "signal": {
          "half_impact_size_": 1.0,
          "length_in_ticks_": 500.0,
          "market_data_": {
           "config_": {
            "exchDt_begin": 10000,
            "exchDt_end": 9223372036854775807,
            "humanSize_": false,
            "initialQty_begin": 0,
            "initialQty_end": 2147483647,
            "qtyCap_": 2147483647,
            "receiveDt_begin": -9223372036854775808,
            "receiveDt_end": 9223372036854775807,
            "type": "SplitMarketData::Config",
            "useSplitBookInTrades": true
           },
           "symbol_": "CME:ZF%0Q",
           "type": "SplitMarketData"
          },
          "name": "SigmoidSVZF_1c500tSlow10us_2697",
          "type": "SigmoidSV"
         },
         "weight": 0.00015638613204991511
        },
        {
         "signal": {
          "half_impact_size_": 500.0,
          "length_in_ticks_": 20.0,
          "market_data_": {
           "symbol_": "CME:ZF%0Q",
           "type": "RawMarketData_Event"
          },
          "name": "SigmoidSVZF_500c20t_9285",
          "type": "SigmoidSV"
         },
         "weight": 0.0006596899892819798
        }
       ]
      },
      "name": "Valuation_AeXw",
      "type": "LinearModel"
     }
    }
   ],
   "utilityNodes": [
    {
     "end_hour_": 17.25,
     "time_zone_": "America/New_York",
     "type": "ReplayKillEOD"
    }
   ],
   "valuations": {
    "Valuation_AeXw": {
     "config_": {
      "name": "Valuation_AeXw",
      "symbol": "CME:ZF%0Q",
      "valuation": [
       {
        "signal": {
         "half_impact_size_": 500.0,
         "length_in_ticks_": 2000.0,
         "market_data_": {
          "symbol_": "CME:ZT%0Q",
          "type": "RawMarketData_Event"
         },
         "name": "SigmoidSVZT_500c2000t_4397",
         "type": "SigmoidSV"
        },
        "weight": 0.0001007627875517353
       },
       {
        "signal": {
         "fast_half_impact_size_": 100.0,
         "fast_length_in_ticks_": 10,
         "market_data_": {
          "config_": {
           "exchDt_begin": 10000,
           "exchDt_end": 9223372036854775807,
           "humanSize_": false,
           "initialQty_begin": 0,
           "initialQty_end": 2147483647,
           "qtyCap_": 2147483647,
           "receiveDt_begin": -9223372036854775808,
           "receiveDt_end": 9223372036854775807,
           "type": "SplitMarketData::Config",
           "useSplitBookInTrades": true
          },
          "symbol_": "CME:ZF%0Q",
          "type": "SplitMarketData"
         },
         "name": "PersistentSVZF_100c10t_1000c100tSlow10us_1217",
         "slow_half_impact_size_": 1000.0,
         "slow_length_in_ticks_": 100,
         "type": "PersistentSV"
        },
        "weight": 0.00017693910733932068
       },
       {
        "signal": {
         "half_impact_size_": 500.0,
         "length_in_ticks_": 2000.0,
         "market_data_": {
          "symbol_": "CME:ZN%0Q",
          "type": "RawMarketData_Event"
         },
         "name": "SigmoidSVZN_500c2000t_5560",
         "type": "SigmoidSV"
        },
        "weight": 0.000883127118472619
       },
       {
        "signal": {
         "fast_half_impact_size_": 100.0,
         "fast_length_in_ticks_": 10,
         "market_data_": {
          "config_": {
           "exchDt_begin": -9223372036854775808,
           "exchDt_end": 9223372036854775807,
           "humanSize_": false,
           "initialQty_begin": 0,
           "initialQty_end": 10,
           "qtyCap_": 2147483647,
           "receiveDt_begin": -9223372036854775808,
           "receiveDt_end": 9223372036854775807,
           "type": "SplitMarketData::Config",
           "useSplitBookInTrades": true
          },
          "symbol_": "CME:ZF%0Q",
          "type": "SplitMarketData"
         },
         "name": "PersistentSVZF_100c10t_1000c100tSmall10_5420",
         "slow_half_impact_size_": 1000.0,
         "slow_length_in_ticks_": 100,
         "type": "PersistentSV"
        },
        "weight": 0.001294890467701194
       },
       {
        "signal": {
         "fill_depth_": 2,
         "market_data_": {
          "config_": {
           "exchDt_begin": -9223372036854775808,
           "exchDt_end": 9223372036854775807,
           "humanSize_": false,
           "initialQty_begin": 0,
           "initialQty_end": 50,
           "qtyCap_": 2147483647,
           "receiveDt_begin": -9223372036854775808,
           "receiveDt_end": 9223372036854775807,
           "type": "SplitMarketData::Config",
           "useSplitBookInTrades": false
          },
          "symbol_": "CME:ZF%0Q",
          "type": "SplitMarketData"
         },
         "name": "FillAveSizeZFSmall50MD2_3908",
         "size_depth_": 2,
         "size_ema_length_": 100000.0,
         "size_mult_": 0.5,
         "type": "FillAve",
         "use_counts_": false
        },
        "weight": 0.2755638769697063
       },
       {
        "signal": {
         "fill_depth_": 2,
         "market_data_": {
          "config_": {
           "exchDt_begin": 10000,
           "exchDt_end": 9223372036854775807,
           "humanSize_": false,
           "initialQty_begin": 0,
           "initialQty_end": 50,
           "qtyCap_": 2147483647,
           "receiveDt_begin": -9223372036854775808,
           "receiveDt_end": 9223372036854775807,
           "type": "SplitMarketData::Config",
           "useSplitBookInTrades": false
          },
          "symbol_": "CME:ZF%0Q",
          "type": "SplitMarketData"
         },
         "name": "FillAveSizeZFSlow10usSmall50MD2_6624",
         "size_depth_": 2,
         "size_ema_length_": 100000.0,
         "size_mult_": 0.5,
         "type": "FillAve",
         "use_counts_": false
        },
        "weight": 0.12030426337298285
       },
       {
        "signal": {
         "fill_depth_": 2,
         "market_data_": {
          "config_": {
           "exchDt_begin": 1000000,
           "exchDt_end": 9223372036854775807,
           "humanSize_": false,
           "initialQty_begin": 10,
           "initialQty_end": 2147483647,
           "qtyCap_": 2147483647,
           "receiveDt_begin": -9223372036854775808,
           "receiveDt_end": 9223372036854775807,
           "type": "SplitMarketData::Config",
           "useSplitBookInTrades": false
          },
          "symbol_": "CME:ZF%0Q",
          "type": "SplitMarketData"
         },
         "name": "FillAveSizeZFSlow1msBig10MD2_7086",
         "size_depth_": 2,
         "size_ema_length_": 100000.0,
         "size_mult_": 0.5,
         "type": "FillAve",
         "use_counts_": false
        },
        "weight": 0.12382430439836066
       },
       {
        "signal": {
         "half_impact_size_": 1.0,
         "length_in_ticks_": 20.0,
         "market_data_": {
          "symbol_": "CME:ZN%0Q",
          "type": "RawMarketData_Event"
         },
         "name": "SigmoidSVZN_1c20t_2901",
         "type": "SigmoidSV"
        },
        "weight": 0.0004356762231873615
       },
       {
        "signal": {
         "half_impact_size1_": 30.0,
         "half_impact_size2_": 20.0,
         "length_in_ticks_": 50,
         "md1_": {
          "symbol_": "CME:ZF%0Q",
          "type": "RawMarketData_Event"
         },
         "md2_": {
          "symbol_": "CME:ZN%0Q",
          "type": "RawMarketData_Event"
         },
         "name": "ProdSVZFZN_30c50t_20c50t_5075",
         "type": "ProdSV"
        },
        "weight": 8.400126816331024e-05
       },
       {
        "signal": {
         "base_theo_": {
          "fill_depth_": 4,
          "market_data_": {
           "config_": {
            "exchDt_begin": -9223372036854775808,
            "exchDt_end": 9223372036854775807,
            "humanSize_": false,
            "initialQty_begin": 0,
            "initialQty_end": 2147483647,
            "qtyCap_": 10,
            "receiveDt_begin": -9223372036854775808,
            "receiveDt_end": 9223372036854775807,
            "type": "SplitMarketData::Config",
            "useSplitBookInTrades": false
           },
           "symbol_": "CME:ZF%0Q",
           "type": "SplitMarketData"
          },
          "size_depth_": 3,
          "size_ema_length_": 100000.0,
          "size_mult_": 1.0,
          "type": "FillAve",
          "use_counts_": false
         },
         "intensity_mult_": 10000.0,
         "long_decay_": 600000000000,
         "name": "TICTZFFillAveSizeZN10m10ms10000t55vm_1348",
         "ref_theo_": {
          "fill_depth_": 4,
          "market_data_": {
           "config_": {
            "exchDt_begin": -9223372036854775808,
            "exchDt_end": 9223372036854775807,
            "humanSize_": false,
            "initialQty_begin": 0,
            "initialQty_end": 2147483647,
            "qtyCap_": 10,
            "receiveDt_begin": -9223372036854775808,
            "receiveDt_end": 9223372036854775807,
            "type": "SplitMarketData::Config",
            "useSplitBookInTrades": false
           },
           "symbol_": "CME:ZN%0Q",
           "type": "SplitMarketData"
          },
          "size_depth_": 3,
          "size_ema_length_": 100000.0,
          "size_mult_": 1.0,
          "type": "FillAve",
          "use_counts_": false
         },
         "short_decay_": 10000000,
         "type": "TradeIntensityCompTheo",
         "vol_mult_": 0.5551515151515152
        },
        "weight": 0.06232185720271092
       },
       {
        "signal": {
         "base_theo_": {
          "fill_depth_": 4,
          "market_data_": {
           "config_": {
            "exchDt_begin": -9223372036854775808,
            "exchDt_end": 9223372036854775807,
            "humanSize_": false,
            "initialQty_begin": 0,
            "initialQty_end": 2147483647,
            "qtyCap_": 10,
            "receiveDt_begin": -9223372036854775808,
            "receiveDt_end": 9223372036854775807,
            "type": "SplitMarketData::Config",
            "useSplitBookInTrades": false
           },
           "symbol_": "CME:ZF%0Q",
           "type": "SplitMarketData"
          },
          "size_depth_": 3,
          "size_ema_length_": 100000.0,
          "size_mult_": 1.0,
          "type": "FillAve",
          "use_counts_": false
         },
         "ema_length_": 600000000000,
         "name": "TimeCompTheoZFFillAveSizeZT10m244vm_1653",
         "ref_theo_": {
          "fill_depth_": 4,
          "market_data_": {
           "config_": {
            "exchDt_begin": -9223372036854775808,
            "exchDt_end": 9223372036854775807,
            "humanSize_": false,
            "initialQty_begin": 0,
            "initialQty_end": 2147483647,
            "qtyCap_": 10,
            "receiveDt_begin": -9223372036854775808,
            "receiveDt_end": 9223372036854775807,
            "type": "SplitMarketData::Config",
            "useSplitBookInTrades": false
           },
           "symbol_": "CME:ZT%0Q",
           "type": "SplitMarketData"
          },
          "size_depth_": 3,
          "size_ema_length_": 100000.0,
          "size_mult_": 1.0,
          "type": "FillAve",
          "use_counts_": false
         },
         "type": "TimeCompTheo",
         "vol_mult_": 2.4426666666666668
        },
        "weight": 0.014834781948862237
       },
       {
        "signal": {
         "base_theo_": {
          "fill_depth_": 4,
          "market_data_": {
           "config_": {
            "exchDt_begin": -9223372036854775808,
            "exchDt_end": 9223372036854775807,
            "humanSize_": false,
            "initialQty_begin": 0,
            "initialQty_end": 2147483647,
            "qtyCap_": 10,
            "receiveDt_begin": -9223372036854775808,
            "receiveDt_end": 9223372036854775807,
            "type": "SplitMarketData::Config",
            "useSplitBookInTrades": false
           },
           "symbol_": "CME:ZF%0Q",
           "type": "SplitMarketData"
          },
          "size_depth_": 3,
          "size_ema_length_": 100000.0,
          "size_mult_": 1.0,
          "type": "FillAve",
          "use_counts_": false
         },
         "intensity_mult_": 10000.0,
         "long_decay_": 600000000000,
         "name": "TICTZFFillAveSizeZT10m10s10000t244vm_1336",
         "ref_theo_": {
          "fill_depth_": 4,
          "market_data_": {
           "config_": {
            "exchDt_begin": -9223372036854775808,
            "exchDt_end": 9223372036854775807,
            "humanSize_": false,
            "initialQty_begin": 0,
            "initialQty_end": 2147483647,
            "qtyCap_": 10,
            "receiveDt_begin": -9223372036854775808,
            "receiveDt_end": 9223372036854775807,
            "type": "SplitMarketData::Config",
            "useSplitBookInTrades": false
           },
           "symbol_": "CME:ZT%0Q",
           "type": "SplitMarketData"
          },
          "size_depth_": 3,
          "size_ema_length_": 100000.0,
          "size_mult_": 1.0,
          "type": "FillAve",
          "use_counts_": false
         },
         "short_decay_": 10000000000,
         "type": "TradeIntensityCompTheo",
         "vol_mult_": 2.4426666666666668
        },
        "weight": 0.09821639797430351
       },
       {
        "signal": {
         "market_data_": {
          "symbol_": "CME:ZF%0Q",
          "type": "RawMarketData_Event"
         },
         "name": "TimeVWAPCompTheoZFMidptZN10ms100vm_1428",
         "nano_vwap_length_": 10000000,
         "ref_theo_": {
          "market_data_": {
           "symbol_": "CME:ZN%0Q",
           "type": "RawMarketData_Event"
          },
          "type": "Midpt"
         },
         "type": "TimeVWAPCompTheo",
         "vol_mult_": 1.0
        },
        "weight": 0.011877958473329094
       },
       {
        "signal": {
         "fill_depth_": 2,
         "market_data_": {
          "symbol_": "CME:ZF%0Q",
          "type": "IcebergTotalRefresh"
         },
         "name": "FillAveSizeZFIcebergRefreshMD3_8128",
         "size_depth_": 3,
         "size_ema_length_": 100000.0,
         "size_mult_": 1.0,
         "type": "FillAve",
         "use_counts_": false
        },
        "weight": 0.041298804587319604
       },
       {
        "signal": {
         "market_data_": {
          "config_": {
           "exchDt_begin": 10000,
           "exchDt_end": 9223372036854775807,
           "humanSize_": false,
           "initialQty_begin": 0,
           "initialQty_end": 2147483647,
           "qtyCap_": 2147483647,
           "receiveDt_begin": -9223372036854775808,
           "receiveDt_end": 9223372036854775807,
           "type": "SplitMarketData::Config",
           "useSplitBookInTrades": true
          },
          "symbol_": "CME:ZF%0Q",
          "type": "SplitMarketData"
         },
         "min_size_": 1,
         "name": "DurationSVZF_1c1msSlow10us_3868",
         "nanos_": 1000000,
         "type": "DurationSV"
        },
        "weight": 9.786430465597851e-05
       },
       {
        "signal": {
         "fill_depth_": 2,
         "market_data_": {
          "config_": {
           "exchDt_begin": -9223372036854775808,
           "exchDt_end": 9223372036854775807,
           "humanSize_": true,
           "initialQty_begin": 0,
           "initialQty_end": 2147483647,
           "qtyCap_": 2147483647,
           "receiveDt_begin": -9223372036854775808,
           "receiveDt_end": 9223372036854775807,
           "type": "SplitMarketData::Config",
           "useSplitBookInTrades": true
          },
          "symbol_": "CME:ZF%0Q",
          "type": "SplitMarketData"
         },
         "name": "FillAveSizeZFHumanSizeMD2_5400",
         "size_depth_": 2,
         "size_ema_length_": 100000.0,
         "size_mult_": 0.5,
         "type": "FillAve",
         "use_counts_": false
        },
        "weight": 0.10076216309126965
       },
       {
        "signal": {
         "market_data_": {
          "config_": {
           "exchDt_begin": -9223372036854775808,
           "exchDt_end": 9223372036854775807,
           "humanSize_": true,
           "initialQty_begin": 0,
           "initialQty_end": 2147483647,
           "qtyCap_": 2147483647,
           "receiveDt_begin": -9223372036854775808,
           "receiveDt_end": 9223372036854775807,
           "type": "SplitMarketData::Config",
           "useSplitBookInTrades": true
          },
          "symbol_": "CME:ZF%0Q",
          "type": "SplitMarketData"
         },
         "min_size_": 1,
         "name": "DurationSVZF_1c1msHuman_5936",
         "nanos_": 1000000,
         "type": "DurationSV"
        },
        "weight": 8.372296697687381e-05
       },
       {
        "signal": {
         "market_data_": {
          "symbol_": "CME:ZF%0Q",
          "type": "RawMarketData_Event"
         },
         "name": "TimeVWAPCompTheoZFMidptZN1m100vm_2658",
         "nano_vwap_length_": 60000000000,
         "ref_theo_": {
          "market_data_": {
           "symbol_": "CME:ZN%0Q",
           "type": "RawMarketData_Event"
          },
          "type": "Midpt"
         },
         "type": "TimeVWAPCompTheo",
         "vol_mult_": 1.0
        },
        "weight": 0.007658826027623614
       },
       {
        "signal": {
         "market_data_": {
          "config_": {
           "exchDt_begin": -9223372036854775808,
           "exchDt_end": 1000,
           "humanSize_": false,
           "initialQty_begin": 0,
           "initialQty_end": 2147483647,
           "qtyCap_": 2147483647,
           "receiveDt_begin": -9223372036854775808,
           "receiveDt_end": 9223372036854775807,
           "type": "SplitMarketData::Config",
           "useSplitBookInTrades": true
          },
          "symbol_": "CME:ZF%0Q",
          "type": "SplitMarketData"
         },
         "min_size_": 50,
         "name": "DurationSVZF_50c50msFast1us_8001",
         "nanos_": 50000000,
         "type": "DurationSV"
        },
        "weight": 0.00021827750452419733
       },
       {
        "signal": {
         "half_impact_size_": 1.0,
         "length_in_ticks_": 2000.0,
         "market_data_": {
          "symbol_": "CME:ZT%0Q",
          "type": "RawMarketData_Event"
         },
         "name": "SigmoidSVZT_1c2000t_8693",
         "type": "SigmoidSV"
        },
        "weight": 4.330828084805216e-05
       },
       {
        "signal": {
         "half_impact_size_": 500.0,
         "length_in_ticks_": 500.0,
         "market_data_": {
          "config_": {
           "exchDt_begin": 10000,
           "exchDt_end": 9223372036854775807,
           "humanSize_": false,
           "initialQty_begin": 0,
           "initialQty_end": 2147483647,
           "qtyCap_": 2147483647,
           "receiveDt_begin": -9223372036854775808,
           "receiveDt_end": 9223372036854775807,
           "type": "SplitMarketData::Config",
           "useSplitBookInTrades": true
          },
          "symbol_": "CME:ZF%0Q",
          "type": "SplitMarketData"
         },
         "name": "SigmoidSVZF_500c500tSlow10us_1700",
         "type": "SigmoidSV"
        },
        "weight": 9.775198180492907e-05
       },
       {
        "signal": {
         "base_theo_": {
          "fill_depth_": 4,
          "market_data_": {
           "config_": {
            "exchDt_begin": -9223372036854775808,
            "exchDt_end": 9223372036854775807,
            "humanSize_": false,
            "initialQty_begin": 0,
            "initialQty_end": 2147483647,
            "qtyCap_": 10,
            "receiveDt_begin": -9223372036854775808,
            "receiveDt_end": 9223372036854775807,
            "type": "SplitMarketData::Config",
            "useSplitBookInTrades": false
           },
           "symbol_": "CME:ZF%0Q",
           "type": "SplitMarketData"
          },
          "size_depth_": 3,
          "size_ema_length_": 100000.0,
          "size_mult_": 1.0,
          "type": "FillAve",
          "use_counts_": false
         },
         "ema_length_": 20000.0,
         "name": "TickCompTheoZFFillAveSizeZN20000t55vm_1297",
         "ref_theo_": {
          "fill_depth_": 4,
          "market_data_": {
           "config_": {
            "exchDt_begin": -9223372036854775808,
            "exchDt_end": 9223372036854775807,
            "humanSize_": false,
            "initialQty_begin": 0,
            "initialQty_end": 2147483647,
            "qtyCap_": 10,
            "receiveDt_begin": -9223372036854775808,
            "receiveDt_end": 9223372036854775807,
            "type": "SplitMarketData::Config",
            "useSplitBookInTrades": false
           },
           "symbol_": "CME:ZN%0Q",
           "type": "SplitMarketData"
          },
          "size_depth_": 3,
          "size_ema_length_": 100000.0,
          "size_mult_": 1.0,
          "type": "FillAve",
          "use_counts_": false
         },
         "type": "TickCompTheo",
         "vol_mult_": 0.5551515151515152
        },
        "weight": 0.14333789238905922
       },
       {
        "signal": {
         "market_data_": {
          "symbol_": "CME:ZF%0Q",
          "type": "RawMarketData_Event"
         },
         "min_size_": 1,
         "name": "DurationSVZF_1c1ms_1422",
         "nanos_": 1000000,
         "type": "DurationSV"
        },
        "weight": 6.164575058704638e-05
       },
       {
        "signal": {
         "half_impact_size_": 10.0,
         "length_in_ticks_": 50000.0,
         "market_data_": {
          "config_": {
           "exchDt_begin": -9223372036854775808,
           "exchDt_end": 1000,
           "humanSize_": false,
           "initialQty_begin": 0,
           "initialQty_end": 2147483647,
           "qtyCap_": 2147483647,
           "receiveDt_begin": -9223372036854775808,
           "receiveDt_end": 9223372036854775807,
           "type": "SplitMarketData::Config",
           "useSplitBookInTrades": true
          },
          "symbol_": "CME:ZF%0Q",
          "type": "SplitMarketData"
         },
         "name": "EMSSigmoidSVZF_10c50000tFast1us_1829",
         "type": "EMSSigmoidSV"
        },
        "weight": 3.833675131597638e-05
       },
       {
        "signal": {
         "half_impact_size_": 500.0,
         "length_in_ticks_": 500.0,
         "market_data_": {
          "config_": {
           "exchDt_begin": -9223372036854775808,
           "exchDt_end": 1000,
           "humanSize_": false,
           "initialQty_begin": 0,
           "initialQty_end": 2147483647,
           "qtyCap_": 2147483647,
           "receiveDt_begin": -9223372036854775808,
           "receiveDt_end": 9223372036854775807,
           "type": "SplitMarketData::Config",
           "useSplitBookInTrades": true
          },
          "symbol_": "CME:ZF%0Q",
          "type": "SplitMarketData"
         },
         "name": "SigmoidSVZF_500c500tFast1us_4861",
         "type": "SigmoidSV"
        },
        "weight": 0.0030797564656540283
       },
       {
        "signal": {
         "half_impact_size_": 1.0,
         "length_in_ticks_": 500.0,
         "market_data_": {
          "config_": {
           "exchDt_begin": 10000,
           "exchDt_end": 9223372036854775807,
           "humanSize_": false,
           "initialQty_begin": 0,
           "initialQty_end": 2147483647,
           "qtyCap_": 2147483647,
           "receiveDt_begin": -9223372036854775808,
           "receiveDt_end": 9223372036854775807,
           "type": "SplitMarketData::Config",
           "useSplitBookInTrades": true
          },
          "symbol_": "CME:ZF%0Q",
          "type": "SplitMarketData"
         },
         "name": "SigmoidSVZF_1c500tSlow10us_2697",
         "type": "SigmoidSV"
        },
        "weight": 0.00015638613204991511
       },
       {
        "signal": {
         "half_impact_size_": 500.0,
         "length_in_ticks_": 20.0,
         "market_data_": {
          "symbol_": "CME:ZF%0Q",
          "type": "RawMarketData_Event"
         },
         "name": "SigmoidSVZF_500c20t_9285",
         "type": "SigmoidSV"
        },
        "weight": 0.0006596899892819798
       }
      ]
     },
     "name": "Valuation_AeXw",
     "type": "LinearModel"
    }
   }
  }
 ],
 "serializeVersion": 3
}